{
  "entities": [
    {
      "id": "dieu_16_2024",
      "label": "DieuLuat",
      "properties": {
        "name": "Điều 16. Trách nhiệm của Nhà nước về đất đai đối với đồng bào dân tộc thiểu số",
        "ma_dieu": "16",
        "phien_ban": 2024,
        "noi_dung": "Điều 16.\n\nTrách nhiệm của Nhà nước về đất đai đối với đồng bào dân tộc thiểu số\n1. Có chính sách bảo đảm đất sinh hoạt cộng đồng cho đồng bào dân tộc thiểu số phù hợp với phong\ntục, tập quán, tín ngưỡng, bản sắc văn hóa và điều kiện thực tế của từng vùng.\n2. Có chính sách hỗ trợ đất đai lần đầu cho cá nhân là người dân tộc thiểu số thuộc diện hộ nghèo, hộ\ncận nghèo tại vùng đồng bào dân tộc thiểu số và miền núi, phù hợp với phong tục, tập quán, tín\nngưỡng, bản sắc văn hóa và điều kiện thực tế của từng vùng để bảo đảm ổn định cuộc sống như sau:\na) Giao đất ở trong hạn mức và được miễn, giảm tiền sử dụng đất;\nb) Cho phép chuyển mục đích sử dụng đất sang đất ở trong hạn mức giao đất ở và được miễn, giảm\ntiền sử dụng đất đối với đất có nguồn gốc được Nhà nước giao, cho thuê, công nhận hoặc được thừa\nkế, tặng cho, nhận chuyển nhượng quyền sử dụng đất theo quy định của pháp luật;\nc) Giao đất nông nghiệp trong hạn mức không thu tiền sử dụng đất;\nd) Cho thuê đất phi nông nghiệp không phải là đất ở để sản xuất, kinh doanh và được miễn, giảm tiền\nthuê đất;\nđ) Diện tích giao đất, cho phép chuyển mục đích sử dụng đất quy định tại điểm a và điểm b khoản này\nđược tính cho tổng diện tích đất được Nhà nước giao, cho phép chuyển mục đích sử dụng đất trong quá\ntrình thực hiện các chính sách về đất đai đối với đồng bào dân tộc thiểu số.\n3. Có chính sách hỗ trợ đất đai để bảo đảm ổn định cuộc sống cho cá nhân là người dân tộc thiểu số đã\nđược Nhà nước giao đất, cho thuê đất quy định tại khoản 2 Điều này nhưng nay không còn đất hoặc about:blank\nthiếu đất so với hạn mức mà thuộc diện hộ nghèo, hộ cận nghèo tại vùng đồng bào dân tộc thiểu số và\nmiền núi như sau:\na) Trường hợp không còn đất ở thì được giao tiếp đất ở, cho phép chuyển mục đích sử dụng đất sang\nđất ở trong hạn mức giao đất ở và được miễn, giảm tiền sử dụng đất. Trường hợp thiếu đất ở thì cho\nphép chuyển mục đích sử dụng đất sang đất ở trong hạn mức giao đất ở và được miễn, giảm tiền sử\ndụng đất;\nb) Trường hợp không còn hoặc thiếu đất nông nghiệp thì được giao tiếp đất nông nghiệp trong hạn\nmức không thu tiền hoặc cho thuê đất phi nông nghiệp không phải là đất ở để sản xuất, kinh doanh và\nđược miễn, giảm tiền thuê đất.\n4. Đất để thực hiện chính sách quy định tại các khoản 1, 2 và 3 Điều này được bố trí từ quỹ đất do cơ\nquan, tổ chức của Nhà nước quản lý hoặc từ quỹ đất thu hồi theo quy định tại  khoản 29 Điều 79 của\nLuật này .\n5. Ủy ban nhân dân cấp tỉnh căn cứ tình hình thực tế và quỹ đất của địa phương quyết định diện tích\ngiao đất, cho thuê đất để thực hiện chính sách hỗ trợ đất đai đối với cá nhân là người dân tộc thiểu số\ntheo quy định tại khoản 3 Điều này .\n6. Ủy ban nhân dân cấp tỉnh trình Hội đồng nhân dân cùng cấp ban hành  chính sách của địa phương về\nđất đai đối với đồng bào dân tộc thiểu số sinh sống trên địa bàn phù hợp với điều kiện thực tế của địa\nphương và tổ chức thực hiện.\n7. Hằng năm, Ủy ban nhân dân cấp xã rà soát, báo cáo Ủy ban nhân dân cấp huyện về các trường hợp\nkhông còn, thiếu hoặc không có đất để giao đất, cho thuê đất theo quy định tại khoản 2 và khoản 3 Điều\nnày; các trường hợp vi phạm chính sách về đất đai đối với đồng bào dân tộc thiểu số, các trường hợp\nđã được Nhà nước giao đất, cho thuê đất theo quy định tại khoản 3 Điều này mà không còn nhu cầu sử\ndụng đất mà phải thu hồi đất để tiếp tục thực hiện chính sách về đất đai đối với đồng bào dân tộc thiểu\nsố quy định tại Điều này .\n8. Kinh phí thực hiện bồi thường, hỗ trợ, tái định cư để thu hồi đất theo quy định tại  khoản 29 Điều 79\ncủa Luật này ; kinh phí đo đạc, lập hồ sơ địa chính, cấp Giấy chứng nhận quyền sử dụng đất, quyền sở\nhữu tài sản gắn liền với đất và các chi phí khác để thực hiện chính sách về đất đai đối với đồng bào\ndân tộc thiểu số được bố trí từ ngân sách nhà nước và nguồn vốn hợp pháp khác theo quy định của\npháp luật.\n9. Chính phủ quy định chi tiết Điều này ."
      }
    },
    {
      "id": "chuthe_nhanuoc",
      "label": "ChuThe",
      "properties": {
        "name": "Nhà nước"
      }
    },
    {
      "id": "chuthe_dongbaodantocthieuso",
      "label": "ChuThe",
      "properties": {
        "name": "đồng bào dân tộc thiểu số"
      }
    },
    {
      "id": "khainiem_datsinhhoatcongdong",
      "label": "KhaiNiem",
      "properties": {
        "name": "đất sinh hoạt cộng đồng"
      }
    },
    {
      "id": "khainiem_chinhsachhotrodatdai",
      "label": "KhaiNiem",
      "properties": {
        "name": "chính sách hỗ trợ đất đai"
      }
    },
    {
      "id": "chuthe_canhannguoidantocthieuso",
      "label": "ChuThe",
      "properties": {
        "name": "cá nhân là người dân tộc thiểu số"
      }
    },
    {
      "id": "chuthe_hogheo",
      "label": "ChuThe",
      "properties": {
        "name": "hộ nghèo"
      }
    },
    {
      "id": "chuthe_hocangheo",
      "label": "ChuThe",
      "properties": {
        "name": "hộ cận nghèo"
      }
    },
    {
      "id": "hanhviphaply_giaodat",
      "label": "HanhViPhapLy",
      "properties": {
        "name": "Giao đất"
      }
    },
    {
      "id": "khainiem_dato",
      "label": "KhaiNiem",
      "properties": {
        "name": "đất ở"
      }
    },
    {
      "id": "hanhviphaply_chuyenmucdichsudungdat",
      "label": "HanhViPhapLy",
      "properties": {
        "name": "chuyển mục đích sử dụng đất"
      }
    },
    {
      "id": "hanhviphaply_chothuedat",
      "label": "HanhViPhapLy",
      "properties": {
        "name": "Cho thuê đất"
      }
    },
    {
      "id": "khainiem_datnongnghiep",
      "label": "KhaiNiem",
      "properties": {
        "name": "đất nông nghiệp"
      }
    },
    {
      "id": "khainiem_datphinongnghiep",
      "label": "KhaiNiem",
      "properties": {
        "name": "đất phi nông nghiệp"
      }
    },
    {
      "id": "chuthe_ubndcaptinh",
      "label": "ChuThe",
      "properties": {
        "name": "Ủy ban nhân dân cấp tỉnh"
      }
    },
    {
      "id": "chuthe_ubndcaphuyen",
      "label": "ChuThe",
      "properties": {
        "name": "Ủy ban nhân dân cấp huyện"
      }
    },
    {
      "id": "chuthe_ubndcapxa",
      "label": "ChuThe",
      "properties": {
        "name": "Ủy ban nhân dân cấp xã"
      }
    },
    {
      "id": "chuthe_chinhphu",
      "label": "ChuThe",
      "properties": {
        "name": "Chính phủ"
      }
    },
    {
      "id": "khainiem_quydat",
      "label": "KhaiNiem",
      "properties": {
        "name": "quỹ đất"
      }
    }
  ],
  "relationships": [
    {
      "source_id": "dieu_16_2024",
      "target_id": "chuthe_nhanuoc",
      "relationship_type": "QUY_DINH_VE"
    },
    {
      "source_id": "dieu_16_2024",
      "target_id": "chuthe_dongbaodantocthieuso",
      "relationship_type": "QUY_DINH_VE"
    },
    {
      "source_id": "dieu_16_2024",
      "target_id": "khainiem_datsinhhoatcongdong",
      "relationship_type": "QUY_DINH_VE"
    },
    {
      "source_id": "dieu_16_2024",
      "target_id": "khainiem_chinhsachhotrodatdai",
      "relationship_type": "QUY_DINH_VE"
    },
    {
      "source_id": "dieu_16_2024",
      "target_id": "chuthe_canhannguoidantocthieuso",
      "relationship_type": "QUY_DINH_VE"
    },
    {
      "source_id": "dieu_16_2024",
      "target_id": "chuthe_hogheo",
      "relationship_type": "QUY_DINH_VE"
    },
    {
      "source_id": "dieu_16_2024",
      "target_id": "chuthe_hocangheo",
      "relationship_type": "QUY_DINH_VE"
    },
    {
      "source_id": "dieu_16_2024",
      "target_id": "hanhviphaply_giaodat",
      "relationship_type": "QUY_DINH_VE"
    },
    {
      "source_id": "dieu_16_2024",
      "target_id": "khainiem_dato",
      "relationship_type": "QUY_DINH_VE"
    },
    {
      "source_id": "dieu_16_2024",
      "target_id": "hanhviphaply_chuyenmucdichsudungdat",
      "relationship_type": "QUY_DINH_VE"
    },
    {
      "source_id": "dieu_16_2024",
      "target_id": "hanhviphaply_chothuedat",
      "relationship_type": "QUY_DINH_VE"
    },
    {
      "source_id": "dieu_16_2024",
      "target_id": "khainiem_datnongnghiep",
      "relationship_type": "QUY_DINH_VE"
    },
    {
      "source_id": "dieu_16_2024",
      "target_id": "khainiem_datphinongnghiep",
      "relationship_type": "QUY_DINH_VE"
    },
    {
      "source_id": "dieu_16_2024",
      "target_id": "chuthe_ubndcaptinh",
      "relationship_type": "QUY_DINH_VE"
    },
    {
      "source_id": "dieu_16_2024",
      "target_id": "chuthe_ubndcaphuyen",
      "relationship_type": "QUY_DINH_VE"
    },
    {
      "source_id": "dieu_16_2024",
      "target_id": "chuthe_ubndcapxa",
      "relationship_type": "QUY_DINH_VE"
    },
    {
      "source_id": "dieu_16_2024",
      "target_id": "chuthe_chinhphu",
      "relationship_type": "QUY_DINH_VE"
    },
    {
      "source_id": "dieu_16_2024",
      "target_id": "khainiem_quydat",
      "relationship_type": "QUY_DINH_VE"
    }
  ]
}